kbkit/__init__.py
kbkit/_version.py
kbkit/analysis/__init__.py
kbkit/analysis/kb_integrator.py
kbkit/analysis/kb_thermo.py
kbkit/analysis/system_state.py
kbkit/calculators/__init__.py
kbkit/calculators/kbi_calculator.py
kbkit/calculators/static_structure_calculator.py
kbkit/config/__init__.py
kbkit/config/mplstyle.py
kbkit/config/presentation.mplstyle
kbkit/config/unit_registry.py
kbkit/core/__init__.py
kbkit/core/kb_pipeline.py
kbkit/core/system_loader.py
kbkit/core/system_properties.py
kbkit/core/system_registry.py
kbkit/data/__init__.py
kbkit/data/gmx_units.json
kbkit/data/property_resolver.py
kbkit/parsers/__init__.py
kbkit/parsers/edr_file.py
kbkit/parsers/gro_file.py
kbkit/parsers/rdf_file.py
kbkit/parsers/top_file.py
kbkit/schema/kbi_metadata.py
kbkit/schema/plot_spec.py
kbkit/schema/system_config.py
kbkit/schema/system_metadata.py
kbkit/schema/thermo_property.py
kbkit/schema/thermo_state.py
kbkit/utils/__init__.py
kbkit/utils/chem.py
kbkit/utils/file_resolver.py
kbkit/utils/format.py
kbkit/utils/io.py
kbkit/utils/logging.py
kbkit/utils/validation.py
kbkit/viz/__init__.py
kbkit/viz/plotter.py
kbkit-1.0.1.dist-info/METADATA
kbkit-1.0.1.dist-info/WHEEL
kbkit-1.0.1.dist-info/licenses/LICENSE
kbkit-1.0.1.dist-info/RECORD
