Metadata-Version: 2.4
Name: kbkit
Version: 1.0.1
Summary: KBKit: Kirkwood-Buff Analysis Toolkit
Author: Allison Peroutka
License: MIT License
License-File: LICENSE
Requires-Python: >=3.10
Requires-Dist: babel<3,>=2.17.0
Requires-Dist: click<9,>=8.2.1
Requires-Dist: furo<2026,>=2025.7.19
Requires-Dist: gromacs<0.0.1,>=0.0.0
Requires-Dist: ipykernel<7,>=6.30.1
Requires-Dist: matplotlib<4,>=3.10.5
Requires-Dist: mdanalysis
Requires-Dist: mpltern<2,>=1.0.4
Requires-Dist: mypy
Requires-Dist: natsort<9,>=8.4.0
Requires-Dist: nbsphinx<0.10,>=0.9.6
Requires-Dist: numpy<3,>=2.3.2
Requires-Dist: pandas<3,>=2.3.1
Requires-Dist: pandoc<3,>=2.4
Requires-Dist: pathlib<2,>=1.0.1
Requires-Dist: pint<0.25
Requires-Dist: plotly<7,>=6.3.0
Requires-Dist: pytest-cov>=6.2.1
Requires-Dist: pytest>=8.4.1
Requires-Dist: rdkit<2026,>=2025.3.5
Requires-Dist: scipy<2,>=1.16.1
Requires-Dist: seaborn<0.14,>=0.13.2
Requires-Dist: sphinx-copybutton<0.6,>=0.5.2
Requires-Dist: sphinx-gallery<0.20,>=0.19.0
Requires-Dist: sphinx-rtd-theme<4,>=3.0.2
Requires-Dist: sphinx>=7.0
Requires-Dist: stubs>=1.0.0
Requires-Dist: sympy<2,>=1.14.0
Requires-Dist: tree-format<0.2,>=0.1.2
Requires-Dist: uncertainties<4,>=3.2.3
